setup.py
zjktest/__init__.py
zjktest/hello.py
zjktest.egg-info/PKG-INFO
zjktest.egg-info/SOURCES.txt
zjktest.egg-info/dependency_links.txt
zjktest.egg-info/requires.txt
zjktest.egg-info/top_level.txt